[{"menu": {
    "sellOff": 0.1,
    "products": [
        {"product": {
            "quantity": 10,
            "price": "15.0",
            "sellOff": "0.2",
            "name": "Donut",
            "id": "PYC-001"
        }},
        {"product": {
            "quantity": 5,
            "price": "20.0",
            "sellOff": "0.0",
            "name": "Amandine",
            "id": "PYC-002"
        }},
        {"product": {
            "quantity": 15,
            "price": "15.0",
            "sellOff": "0.2",
            "name": "Babka",
            "id": "PYC-003"
        }},
        {"product": {
            "quantity": 10,
            "price": "20.0",
            "sellOff": "0.2",
            "name": "Wingko",
            "id": "PYC-004"
        }}
    ]
}}]